vision_xformer/__init__.py
vision_xformer/fnet.py
vision_xformer/fnet2d.py
vision_xformer/vision_linformer.py
vision_xformer/vision_nystromformer.py
vision_xformer/vision_performer.py
vision_xformer-0.2.0.dist-info/LICENSE
vision_xformer-0.2.0.dist-info/METADATA
vision_xformer-0.2.0.dist-info/WHEEL
vision_xformer-0.2.0.dist-info/top_level.txt
vision_xformer-0.2.0.dist-info/RECORD
