Metadata-Version: 2.1
Name: vision-xformer
Version: 0.2.0
Summary: Vision Xformers
Home-page: https://github.com/pranavphoenix/VisionXformer
Author: Pranav Jeevan
Author-email: pranav13phoenix@gmail.com
License: MIT
Keywords: artificial intelligence,training,optimizer,machine learning,attention,transformers,computer vision
Classifier: Development Status :: 4 - Beta
Classifier: Intended Audience :: Developers
Classifier: Topic :: Scientific/Engineering :: Artificial Intelligence
Classifier: License :: OSI Approved :: MIT License
Classifier: Programming Language :: Python :: 3.6
License-File: LICENSE
Requires-Dist: torch
Requires-Dist: torchvision
Requires-Dist: numpy
Requires-Dist: einops
Requires-Dist: performer-pytorch
Requires-Dist: linformer
